samplesizelib/__init__.py
samplesizelib/linear/__init__.py
samplesizelib/linear/bayesian.py
samplesizelib/linear/heuristic.py
samplesizelib/linear/models.py
samplesizelib/linear/statistical.py
samplesizelib/shared/__init__.py
samplesizelib/shared/estimator.py
samplesizelib/shared/utils.py
samplesizelib-0.0.4.dist-info/LICENSE
samplesizelib-0.0.4.dist-info/METADATA
samplesizelib-0.0.4.dist-info/WHEEL
samplesizelib-0.0.4.dist-info/top_level.txt
samplesizelib-0.0.4.dist-info/RECORD
