Metadata-Version: 2.1
Name: samplesizelib
Version: 0.0.4
Summary: sample size lib, python package
Home-page: https://github.com/andriygav/SampleSizeLib
Author: Andrey Grabovoy
Author-email: grabovoy.av@phystech.edu
License: MIT
Platform: UNKNOWN
Requires-Dist: numpy (==1.18.5)
Requires-Dist: scipy (==1.3.3)
Requires-Dist: scikit-learn (==0.23.2)
Requires-Dist: tqdm (==4.46.1)
